[
  {
    "plant_name": "Aconitum",
    "description": "Monkshood/Wolfsbane: Tall perennial with steel blue flowers midsummer. Rich green deeply cut leaves. Prefers rich moist soils. Good cut flower.",
    "hardiness_zone_lower": "2",
    "hardiness_zone_upper": "9",
    "habit": "herb",
    "life_cycle": "perennial",
    "full_sun": true,
    "part_sun": true,
    "part_shade": true,
    "full_shade": false,
    "early_spring": false,
    "mid_spring": false,
    "late_spring": false,
    "early_summer": false,
    "mid_summer": true,
    "late_summer": false,
    "fall": false,
    "winter": false
  },
  {
    "plant_name": "Asclepias tuberosa",
    "description": "Butterfly Weed: Drought tolerant perennial with bright orange blossoms that attract butterflies!",
    "hardiness_zone_lower": "3",
    "hardiness_zone_upper": "9",
    "habit": "herb",
    "life_cycle": "perennial",
    "full_sun": true,
    "part_sun": true,
    "part_shade": true,
    "full_shade": false,
    "early_spring": false,
    "mid_spring": false,
    "late_spring": false,
    "early_summer": true,
    "mid_summer": true,
    "late_summer": true,
    "fall": false,
    "winter": false
  },
  {
    "plant_name": "Deutzia gracillis",
    "description": "Dwarf, dense, rounded, deciduous shrub which forms a graceful, spreading mound. White flowers cover the shrub in late May to early June",
    "hardiness_zone_lower": "4",
    "hardiness_zone_upper": "8",
    "habit": "shrub",
    "life_cycle": "perennial",
    "full_sun": true,
    "part_sun": true,
    "part_shade": true,
    "full_shade": false,
    "early_spring": false,
    "mid_spring": false,
    "late_spring": true,
    "early_summer": false,
    "mid_summer": true,
    "late_summer": false,
    "fall": false,
    "winter": false
  },
  {
    "plant_name": "Ginkgo biloba",
    "description": "Var Goldspire: Narrow pyramidal shape with deep green fan-shaped leaves that turn brilliant yellow in fall.",
    "hardiness_zone_lower": "4",
    "hardiness_zone_upper": "9",
    "habit": "tree",
    "life_cycle": "perennial",
    "full_sun": true,
    "part_sun": true,
    "part_shade": false,
    "full_shade": false,
    "early_spring": false,
    "mid_spring": true,
    "late_spring": true,
    "early_summer": true,
    "mid_summer": true,
    "late_summer": true,
    "fall": true,
    "winter": false
  },
  {
    "plant_name": "Hosta",
    "description": "Krossa Regal. Slug resistant, frosty blue-green leaves with a graceful, vase like habit. Lavender blossoms.",
    "hardiness_zone_lower": 3,
    "hardiness_zone_upper": 9,
    "habit": "herb",
    "life_cycle": "perennial",
    "full_sun": false,
    "part_sun": false,
    "part_shade": true,
    "full_shade": true,
    "early_spring": false,
    "mid_spring": false,
    "late_spring": false,
    "early_summer": false,
    "mid_summer": true,
    "late_summer": true,
    "fall": false,
    "winter": false
  },
  {
    "plant_name": "Ligularia",
    "description": "Ragwort. Part shade. Large, rounded maroon black leaves bearing clusters of golden orange daisy-like flowers in midsummer. Prefers moist soil. Grows 3-4 feet tall.",
    "hardiness_zone_lower": 3,
    "hardiness_zone_upper": 9,
    "habit": "herb",
    "life_cycle": "perennial",
    "full_sun": false,
    "part_sun": false,
    "part_shade": true,
    "full_shade": false,
    "early_spring": false,
    "mid_spring": false,
    "late_spring": false,
    "early_summer": false,
    "mid_summer": true,
    "late_summer": false,
    "fall": false,
    "winter": false
  },
  {
    "plant_name": "Peony",
    "description": "Laura Dessert. Large double, creamy white blossoms with pale lemon yellow center. Fragrant. Deer resistant.",
    "hardiness_zone_lower": 3,
    "hardiness_zone_upper": 8,
    "habit": "herb",
    "life_cycle": "perennial",
    "full_sun": true,
    "part_sun": true,
    "part_shade": false,
    "full_shade": false,
    "early_spring": false,
    "mid_spring": false,
    "late_spring": true,
    "early_summer": true,
    "mid_summer": false,
    "late_summer": false,
    "fall": false,
    "winter": false
  },
  {
    "plant_name": "Peony",
    "description": "Shirley Temple. Opens as a pale pink double blossom that lightens to white as flower ages. Fragrant. Deer resistant.",
    "hardiness_zone_lower": 3,
    "hardiness_zone_upper": 8,
    "habit": "herb",
    "life_cycle": "perennial",
    "full_sun": true,
    "part_sun": true,
    "part_shade": true,
    "full_shade": false,
    "early_spring": false,
    "mid_spring": false,
    "late_spring": true,
    "early_summer": true,
    "mid_summer": false,
    "late_summer": false,
    "fall": false,
    "winter": false
  },
  {
    "plant_name": "Brunnera macrophylla",
    "description": "Bugloss. Var Alexander's Great. King size version of Jack Frost, silver heart-shaped foliage, 12\"x10\" w/ green veins. Prefers moist soils. 15\"Hx28\"W",
    "hardiness_zone_lower": 4,
    "hardiness_zone_upper": 8,
    "habit": "herb",
    "life_cycle": "perennial",
    "full_sun": false,
    "part_sun": true,
    "part_shade": true,
    "full_shade": false,
    "early_spring": false,
    "mid_spring": true,
    "late_spring": true,
    "early_summer": true,
    "mid_summer": true,
    "late_summer": true,
    "fall": false,
    "winter": false
  },
  {
    "plant_name": "Rosa rugosa",
    "description": "Beach Rose, Var Alba. Single, papery white blossoms that open from light pink buds and have contrasting yellow stamens. Followed by reddish-orange hips.",
    "hardiness_zone_lower": 2,
    "hardiness_zone_upper": 9,
    "habit": "shrub",
    "life_cycle": "perennial",
    "full_sun": true,
    "part_sun": true,
    "part_shade": false,
    "full_shade": false,
    "early_spring": false,
    "mid_spring": false,
    "late_spring": true,
    "early_summer": true,
    "mid_summer": true,
    "late_summer": true,
    "fall": false,
    "winter": false
  },
  {
    "plant_name": "Forsythia",
    "description": "Var Lynwood Gold. Deep yellow/gold flowers in early spring before foliage emerges, gracefull arching habit.",
    "hardiness_zone_lower": 2,
    "hardiness_zone_upper": 9,
    "habit": "shrub",
    "life_cycle": "perennial",
    "full_sun": true,
    "part_sun": true,
    "part_shade": false,
    "full_shade": false,
    "early_spring": true,
    "mid_spring": true,
    "late_spring": false,
    "early_summer": false,
    "mid_summer": false,
    "late_summer": false,
    "fall": false,
    "winter": false
  },
  {
    "plant_name": "Viburnum carlesii",
    "description": "Arrowwoord. Var Korean Spice. Large clusters of spicy-scented, waxy pink flowers fade to white followed by bright red berries. Foliage becomes red and burgundy in autumn.",
    "hardiness_zone_lower": 4,
    "hardiness_zone_upper": 8,
    "habit": "shrub",
    "life_cycle": "perennial",
    "full_sun": true,
    "part_sun": true,
    "part_shade": true,
    "full_shade": false,
    "early_spring": false,
    "mid_spring": true,
    "late_spring": true,
    "early_summer": true,
    "mid_summer": true,
    "late_summer": true,
    "fall": true,
    "winter": false
  },
  {
    "plant_name": "Hibiscus",
    "description": "Tree form Rose of Sharon. Var Raspberry Smoothie. Double raspberry colored flowers summer through fall, 8'H x 4'W",
    "hardiness_zone_lower": 5,
    "hardiness_zone_upper": 9,
    "habit": "tree",
    "life_cycle": "perennial",
    "full_sun": true,
    "part_sun": false,
    "part_shade": false,
    "full_shade": false,
    "early_spring": false,
    "mid_spring": false,
    "late_spring": false,
    "early_summer": false,
    "mid_summer": true,
    "late_summer": true,
    "fall": true,
    "winter": false
  }
]